nosql_objects/__init__.py
nosql_objects/admin.py
nosql_objects/apps.py
nosql_objects/models.py
nosql_objects/pagination.py
nosql_objects/permissions.py
nosql_objects/serializers.py
nosql_objects/signals.py
nosql_objects/urls.py
nosql_objects/views.py
nosql_objects/migrations/0001_initial.py
nosql_objects/migrations/__init__.py
django_nosql_objects-1.1.dist-info/LICENSE
django_nosql_objects-1.1.dist-info/METADATA
django_nosql_objects-1.1.dist-info/WHEEL
django_nosql_objects-1.1.dist-info/top_level.txt
django_nosql_objects-1.1.dist-info/RECORD
