Metadata-Version: 2.1
Name: django-nosql-objects
Version: 1.1
Summary: Django_nosql_objects is an app for allowing users store JSON documents
Home-page: https://github.com/osval-do/django-nosql-storage/tree/main
Author: Osvaldo Molina
Author-email: osvaldo.molina.128@gmail.com
License: MIT
Project-URL: Documentation, https://github.com/osval-do/django-nosql-storage
Project-URL: Changelog, https://github.com/osval-do/django-nosql-storage/blob/main/CHANGES.rst
Project-URL: Bug Tracker, https://github.com/osval-do/django-nosql-storage/issues
Project-URL: Source Code, https://github.com/osval-do/django-nosql-storage
Platform: UNKNOWN
Classifier: Development Status :: 5 - Production/Stable
Classifier: Environment :: Web Environment
Classifier: Intended Audience :: Developers
Classifier: License :: OSI Approved :: MIT License
Classifier: Operating System :: OS Independent
Classifier: Framework :: Django
Classifier: Framework :: Django :: 3.2
Classifier: Framework :: Django :: 4.0
Classifier: Framework :: Django :: 4.1
Classifier: Programming Language :: Python
Classifier: Programming Language :: Python :: 3
Classifier: Programming Language :: Python :: 3.7
Classifier: Programming Language :: Python :: 3.8
Classifier: Programming Language :: Python :: 3.9
Classifier: Programming Language :: Python :: 3.10
Requires-Python: >=3.7
License-File: LICENSE
Requires-Dist: Django (>=3.2)
Requires-Dist: django-filter
Requires-Dist: django-guardian
Requires-Dist: djangorestframework
Requires-Dist: djangorestframework-guardian
